ranex-0.1.3.dist-info/METADATA
ranex-0.1.3.dist-info/WHEEL
ranex-0.1.3.dist-info/entry_points.txt
ranex/__init__.py
ranex/__main__.py
ranex/cli.py
ranex/ranex_rust.cp311-win_amd64.pyd
ranex/templates.py
ranex/templates/firewall.yaml
ranex-0.1.3.dist-info/RECORD
