Metadata-Version: 2.4
Name: ranex
Version: 0.1.3
Classifier: Programming Language :: Rust
Classifier: Programming Language :: Python :: Implementation :: CPython
Summary: Python bindings for Ranex - exposes Atlas codebase indexing to Python
